setup.py
vishad_distributions/Binomialdistribution.py
vishad_distributions/Gaussiandistribution.py
vishad_distributions/Generaldistribution.py
vishad_distributions/__init__.py
vishad_distributions.egg-info/PKG-INFO
vishad_distributions.egg-info/SOURCES.txt
vishad_distributions.egg-info/dependency_links.txt
vishad_distributions.egg-info/not-zip-safe
vishad_distributions.egg-info/top_level.txt