Metadata-Version: 1.0
Name: vishad-distributions
Version: 0.1
Summary: Test your Gaussian distributions
Home-page: UNKNOWN
Author: UNKNOWN
Author-email: UNKNOWN
License: UNKNOWN
Platform: UNKNOWN
